{"0Hr+JXeUKsgADXXJwoP1QQ==":"mbr-1643x1080.jpg","bsxRYza7Rsa2udbQIP5RtQ==":"mbr-1440x1080.jpg","0ZXIxUv0dSEC4xceob75nA==":"mbr-1620x1080.jpg","izLPXtta9PbhNpzu7oZl7Q==":"mbr-1-1620x1080.jpg","UGgfuJltZT5o0BH9cU1Zuw==":"mbr-2-1620x1080.jpg","+0/Imh408eBbXWvk/0kknQ==":"mbr-3-1620x1080.jpg","bvJe31FlgVo40z1s6snCVQ==":"mbr-4-1620x1080.jpg","80EiT8iYFNtwBft8OUdKJw==":"mbr-1441x1080.jpg","6CEVq9K/372tRUn01tC27A==":"mbr-720x1080.jpg","yQ8n60TSrGkGkjmk9TJQQQ==":"mbr-1-720x1080.jpg","1s2Y3WUWvJWXrO8HkuBr3Q==":"mbr-1618x1080.jpg","TdbJcBx63KP7ZipzjvfFYg==":"mbr-5-1620x1080.jpg","Q/HVe846/Mvd0S3SYfcd/w==":"mbr-1728x1080.jpg","AB43jJqBTdMeH0GHSkDE1g==":"mbr-1920x1078.jpg","2C1VsSBLNjFGpa7w2JZXOA==":"cody-davis-253928-2000x1333.jpg","rqtHpJaJs4VSyOhXNoUaNw==":"mbr-1-1440x1080.jpg","0q1oIh9UXNYlJHhmIpyWJA==":"mbr-1-1618x1080.jpg"}